virtual_lab/__about__.py
virtual_lab/__init__.py
virtual_lab/agent.py
virtual_lab/constants.py
virtual_lab/prompts.py
virtual_lab/py.typed
virtual_lab/run_meeting.py
virtual_lab/utils.py
virtual_lab-1.2.0.dist-info/METADATA
virtual_lab-1.2.0.dist-info/WHEEL
virtual_lab-1.2.0.dist-info/licenses/LICENSE
virtual_lab-1.2.0.dist-info/RECORD
