Metadata-Version: 2.4
Name: virtual-lab
Version: 1.2.0
Summary: A virtual lab of large language model agents for scientific research.
Project-URL: Homepage, https://github.com/zou-group/virtual-lab
Project-URL: Issues, https://github.com/zou-group/virtual-lab/issues
Author-email: Kyle Swanson <swansonk.14@gmail.com>
Maintainer-email: Kyle Swanson <swansonk.14@gmail.com>
License: MIT License
License-File: LICENSE
Keywords: LLM,automated science,large language model,scientific research,virtual lab
Classifier: License :: OSI Approved :: MIT License
Classifier: Operating System :: OS Independent
Classifier: Programming Language :: Python :: 3
Classifier: Programming Language :: Python :: 3.10
Classifier: Programming Language :: Python :: 3.11
Classifier: Programming Language :: Python :: 3.12
Classifier: Programming Language :: Python :: 3.13
Classifier: Programming Language :: Python :: 3.14
Classifier: Typing :: Typed
Requires-Python: >=3.10
Requires-Dist: notebook
Requires-Dist: openai
Requires-Dist: requests
Requires-Dist: tiktoken
Requires-Dist: tqdm
Requires-Dist: typed-argument-parser
Provides-Extra: nanobody-design
Requires-Dist: biopython; extra == 'nanobody-design'
Requires-Dist: pandas; extra == 'nanobody-design'
Requires-Dist: seaborn; extra == 'nanobody-design'
Requires-Dist: torch; extra == 'nanobody-design'
Requires-Dist: transformers; extra == 'nanobody-design'
